Metadata-Version: 2.1
Name: hypermodern-python-tutorial
Version: 0.1.0
Summary: The hypermodern Python project
Home-page: https://github.com/prometeyqwe/hypermodern-python-tutorial
License: MIT
Keywords: hypermodern
Author: Evgeny Kirillov
Author-email: kirilllov.evgeny@mail.ru
Requires-Python: >=3.10,<4.0
Classifier: License :: OSI Approved :: MIT License
Classifier: Programming Language :: Python :: 3
Classifier: Programming Language :: Python :: 3.10
Classifier: Programming Language :: Python :: 3.11
Requires-Dist: click (>=8.1.3,<9.0.0)
Requires-Dist: desert (>=2022.9.22,<2023.0.0)
Requires-Dist: marshmallow (>=3.19.0,<4.0.0)
Requires-Dist: requests (>=2.28.1,<3.0.0)
Project-URL: Repository, https://github.com/prometeyqwe/hypermodern-python-tutorial
